recursive_import/__init__.py
recursive_import-1.0.0.dist-info/LICENSE
recursive_import-1.0.0.dist-info/METADATA
recursive_import-1.0.0.dist-info/WHEEL
recursive_import-1.0.0.dist-info/top_level.txt
recursive_import-1.0.0.dist-info/RECORD
