Metadata-Version: 2.1
Name: recursive-import
Version: 1.0.0
Summary: Trivial library that will import the whole module tree
Author-email: Filip Malczak <filip.malczak@gmail.com>
License: MIT License
Project-URL: Homepage, https://github.com/FilipMalczak/recursive_import
Keywords: import
Classifier: License :: OSI Approved :: MIT License
Classifier: Programming Language :: Python
Classifier: Programming Language :: Python :: 3
Requires-Python: >=3.5
License-File: LICENSE
